dataset/__init__.py
dataset/data_simulation.py
examples/__init__.py
ibotta_uplift/__init__.py
ibotta_uplift/calibrate_uplift.py
ibotta_uplift/erupt.py
ibotta_uplift/ibotta_uplift.py
ibotta_uplift/keras_model_functionality.py
tests/__init__.py
tests/test_calibrate.py
tests/test_ibotta_uplift.py
ibotta_uplift-0.0.4.dist-info/LICENSE
ibotta_uplift-0.0.4.dist-info/METADATA
ibotta_uplift-0.0.4.dist-info/NOTICE
ibotta_uplift-0.0.4.dist-info/WHEEL
ibotta_uplift-0.0.4.dist-info/top_level.txt
ibotta_uplift-0.0.4.dist-info/RECORD
