Metadata-Version: 2.1
Name: ibotta-uplift
Version: 0.0.4
Summary: Machine learning tools for uplift models
Home-page: UNKNOWN
Author: Ibotta Inc.
Author-email: machine_learning@ibotta.com
License: Apache 2.0
Download-URL: https://github.com/Ibotta/ibotta_uplift
Project-URL: Source Code, https://github.com/Ibotta/ibotta_uplift
Platform: UNKNOWN
Classifier: Intended Audience :: Developers
Classifier: Programming Language :: Python
Classifier: Programming Language :: Python :: 3
Classifier: Programming Language :: Python :: 3.5
Classifier: Programming Language :: Python :: 3.6
Classifier: Programming Language :: Python :: 3.7
Classifier: Programming Language :: Python :: 3.8
Classifier: Topic :: Scientific/Engineering
Requires-Python: >=3.5
Requires-Dist: numpy
Requires-Dist: pandas
Requires-Dist: tensorflow
Requires-Dist: keras
Requires-Dist: dill
Requires-Dist: sklearn
